Workbook
Name Slicer_ACCOUNT: #N/A

Sheet CHART OF ACCOUNT
A1: ACCOUNT | C1: ACCOUNT | D1: SUB ACCOUNT | E1: FINANCIAL STATEMENT | G1: Individual Account | H1: SUB ACCOUNT
A2: Assets | C2: Assets | D2: Current Asset | E2: Balance sheet | G2: Cash | H2: Current Asset
A3: Laibilities | C3: Assets | D3: Fixed Assets | E3: Balance sheet | G3: Equity-Owais | H3: Equity
A4: Equity | C4: Laibilities | D4: Current liabalities | E4: Balance sheet | G4: Bank-112 | H4: Current Asset
A5: Expense | C5: Laibilities | D5: Fixed Laibalities | E5: Balance sheet | G5: Inventory | H5: Current Asset
A6: Revneue | C6: Equity | D6: Equity | E6: Balance sheet | G6: Mr.zubair | H6: Current liabalities
C7: Expense | D7: Expense | E7: Income Statement | G7: Sales | H7: Revneue
C8: Revneue | D8: Revneue | E8: Income Statement | G8: Cost of Good Solds | H8: Expense
C9: Revneue | D9: Contra Revenue | E9: Income Statement | G9: Mr.Ali | H9: Current Asset
G10: Electricity | H10: Expense
G11: Salary | H11: Expense
G12: Taxes | H12: Expense
G13: Govt | H13: Current liabalities
G14: Shop | H14: Fixed assets

Sheet JOURNAL ENTRIES
B1: JOURNAL ENTRIES | H1: *Establising a busniess by Owais, investing Rs 1 million in cash
H2: *Deposit Rs5 lac in Bank on 2 jan 2026
A3: DATE | B3: DESCRIPTION | C3: ACCOUNT | D3: DEBIT | E3: CREDIT | F3: COMMENTS | H3: *purchase inventory on credit for Rs 600000 from Mr. Zubair
A4: 46023 | B4: Estabalising a busniess | C4: Cash | D4: 1000000 | H4: *purchased inventory of RS 200000 bypaying from cheque from Mr.Ahmeed
A5: 46023 | B5: Estabalising a busniess | C5: Equity-Owais | E5: 1000000 | H5: *Sold inventory for Rs 400000 on cash on 10th jan the COGS is 300000
A6: 46024 | B6: Deposit in bank | C6: Bank-112 | D6: 500000 | F6: Mr Ozair went to deposit in bank | H6: *Sold inventory for credit to Mr. ALI for RS.300000 on 15 jan
A7: 46024 | B7: Deposit in bank | C7: Cash | E7: 500000 | H7: *paid elecricty bill for Rs 14000
A8: 46025 | B8: Purchase Inventory | C8: Inventory | D8: 600000 | H8: *Paid salary to employee for Rs 100000 by cash
A9: 46025 | B9: Purchase Inventory | C9: Mr.zubair | E9: 600000 | H9: *paid cash to Mr zubair by cash 100000
A10: 46026 | B10: Purchased Inventory | C10: Inventory | D10: 200000 | H10: *Mr Ali gave the amount of 150000 in bank
A11: 46026 | B11: Purchased Inventory | C11: Bank-112 | E11: 200000
A12: 46032 | B12: Sale Inventory | C12: Cash | D12: 400000
A13: 46032 | B13: Sale Inventory | C13: Sales | E13: 400000
A14: 46032 | B14: Adjust inventory Against COGS | C14: Cost of Good Solds | D14: 300000
A15: 46032 | B15: Adjust inventory Against COGS | C15: Inventory | E15: 300000
A16: 46037 | B16: Sold inventory on Credit | C16: Mr.Ali | D16: 300000
A17: 46037 | B17: Sold inventory on Credit | C17: Sales | E17: 300000
A18: 46037 | B18: Adjust inventory Against COGS | C18: Cost of Good Solds | D18: 150000
A19: 46037 | B19: Adjust inventory Against COGS | C19: Inventory | E19: 150000
A20: 46037 | B20: Paid Electricity Bill | C20: Electricity | D20: 14000
A21: 46037 | B21: Paid Electricity Bill | C21: Bank-112 | E21: 14000
A22: 46052 | B22: Paid Salary | C22: Salary | D22: 100000
A23: 46052 | B23: Paid Salary | C23: Cash | E23: 100000
A24: 46055 | B24: Paid Cash to Mr.Zubair | C24: Mr.zubair | D24: 100000
A25: 46055 | B25: Paid Cash to Mr.Zubair | C25: Cash | E25: 100000
A26: 46059 | B26: Cash received by Mr.Ali | C26: Bank-112 | D26: 150000
A27: 46059 | B27: Cash received by Mr.Ali | C27: Mr.Ali | E27: 150000
A28: 46063 | B28: Purchased a shop | C28: Shop | D28: 100000
A29: 46063 | B29: Purchased a shop | C29: Cash | E29: 100000
A30: 46081 | B30: Payble to Govt | C30: Taxes | D30: 20400
A31: 46081 | B31: Payble to Govt | C31: Govt | E31: 20400

Sheet LEDGER
A2: =C4 -> Cash | C2: =VLOOKUP(A2,'CHART OF ACCOUNT'!G:H,2,0) -> Current Asset
A3: DATE | B3: DESCRIPTION | C3: ACCOUNT | D3: Sum of DEBIT | E3: Sum of CREDIT | F3: Sum of BALANCE
A4: 46023 | B4: Estabalising a busniess | C4: Cash | D4: 1000000 | F4: 1000000
A5: 46024 | B5: Deposit in bank | C5: Cash | E5: 500000 | F5: -500000
A6: 46032 | B6: Sale Inventory | C6: Cash | D6: 400000 | F6: 400000
A7: 46052 | B7: Paid Salary | C7: Cash | E7: 100000 | F7: -100000
A8: 46055 | B8: Paid Cash to Mr.Zubair | C8: Cash | E8: 100000 | F8: -100000
A9: 46063 | B9: Purchased a shop | C9: Cash | E9: 100000 | F9: -100000
A10: Grand Total | D10: 1400000 | E10: 800000 | F10: 600000

Sheet TRAIL BALANCE
A2: TRAIL BALANCE
A3: ACCOUNT | B3: Sum of DEBIT | C3: Sum of CREDIT | D3: Sum of BALANCE
A4: Bank-112 | B4: 650000 | C4: 214000 | D4: 436000
A5: Cash | B5: 1400000 | C5: 800000 | D5: 600000
A6: Cost of Good Solds | B6: 450000 | D6: 450000
A7: Electricity | B7: 14000 | D7: 14000
A8: Equity-Owais | C8: 1000000 | D8: -1000000
A9: Inventory | B9: 800000 | C9: 450000 | D9: 350000
A10: Mr.Ali | B10: 300000 | C10: 150000 | D10: 150000
A11: Mr.zubair | B11: 100000 | C11: 600000 | D11: -500000
A12: Salary | B12: 100000 | D12: 100000
A13: Sales | C13: 700000 | D13: -700000
A14: Taxes | B14: 20400 | D14: 20400
A15: Govt | C15: 20400 | D15: -20400
A16: Shop | B16: 100000 | D16: 100000
A17: Grand Total | B17: 3934400 | C17: 3934400 | D17: 0

Sheet INCOME STATMENT
B2: ABC BANK
B3: INCOME STATEMENT
B4: FOR THE PERIOD OF 2026
C6: SALES | F6: =VLOOKUP(C6,'TRAIL BALANCE'!$A$4:$D$13,4,0)*-1 -> 700000
C7: Cost of Good Solds | F7: =VLOOKUP(C7,'TRAIL BALANCE'!$A$4:$D$13,4,0)*-1 -> -450000
C8: GROSS PROFIT | F8: =F6+F7 -> 250000
C10: OPREATING EXPENSES
C12: Salary | E12: =VLOOKUP(C12,'TRAIL BALANCE'!$A$4:$D$13,4,0) -> 100000
C13: Electricity | E13: =VLOOKUP(C13,'TRAIL BALANCE'!$A$4:$D$13,4,0) -> 14000
C14: Total of Opreating Expenses | F14: =SUM(E12:E13)*-1 -> -114000
C15: Opreating profit | F15: =F8+F14 -> 136000
C16: Tax 15% | F16: =(F15*15%)*-1 -> -20400
C17: Net profit | F17: =F15+F16 -> 115600

Sheet BALANCE SHEET
A1: ABC BANK
A2: BALANCE SHEET
A3: FOR THE YEAR 2026
A5: Assets | F5: Laibalites & Equity
A6: FIXED ASSETS | F6: Laibalities
A7: Shop | D7: =VLOOKUP(A7,'TRAIL BALANCE'!$A$4:$D$16,4,0) -> 100000 | F7: FIXED LIABALITES | J7: 0
A8: Total of fixed Assets | E8: =SUM(D7) -> 100000 | F8: CURRENT LIABALITES
F9: Mr.zubair | I9: =VLOOKUP(F9,'TRAIL BALANCE'!$A$4:$D$16,4,0)*-1 -> 500000
A10: CURRENT ASSETS | F10: Govt | I10: =VLOOKUP(F10,'TRAIL BALANCE'!$A$4:$D$16,4,0)*-1 -> 20400
A11: Bank-112 | D11: =VLOOKUP(A11,'TRAIL BALANCE'!$A$4:$D$16,4,0) -> 436000 | F11: Total of current laibalities | J11: =SUM(I9:I10) -> 520400
A12: Cash | D12: =VLOOKUP(A12,'TRAIL BALANCE'!$A$4:$D$16,4,0) -> 600000
A13: Inventory | D13: =VLOOKUP(A13,'TRAIL BALANCE'!$A$4:$D$16,4,0) -> 350000 | F13: Total of Laibalities | J13: =SUM(J11,J7) -> 520400
A14: Mr.Ali | D14: =VLOOKUP(A14,'TRAIL BALANCE'!$A$4:$D$16,4,0) -> 150000
A15: Total of current assets | E15: =SUM(D11:D14) -> 1536000
F16: Equity
F17: Equity-Owais | I17: =VLOOKUP(F17,'TRAIL BALANCE'!$A$4:$D$16,4,0)*-1 -> 1000000
F18: Retained earning | I18: ='INCOME STATMENT'!F17 -> 115600
F19: Total of equity | J19: =SUM(I17:I18) -> 1115600
A21: TOTAL ASSETS | E21: =SUM(E8,E15) -> 1636000 | F21: TOTAL LAIBALITIES & EQUITY | J21: =SUM(J13,J19) -> 1636000
